chef_msg/__init__.py
chef_msg/mommy.py
chef_msg-0.0.2.dist-info/LICENSE
chef_msg-0.0.2.dist-info/METADATA
chef_msg-0.0.2.dist-info/WHEEL
chef_msg-0.0.2.dist-info/top_level.txt
chef_msg-0.0.2.dist-info/RECORD
