Metadata-Version: 2.1
Name: chef-msg
Version: 0.0.2
Summary: special pre-processing for image
Home-page: https://github.com/sangggho/chef
Author: sangggho
Author-email: sangggho@gmail.com
License: UNKNOWN
Project-URL: Bug Tracker, https://github.com/sangggho/chef/issues
Platform: UNKNOWN
Classifier: Programming Language :: Python :: 3
Classifier: License :: OSI Approved :: MIT License
Classifier: Operating System :: OS Independent
Requires-Python: >=3.8
License-File: LICENSE
